lunarcord/__init__.py
lunarcord/activities.py
lunarcord/basetypes.py
lunarcord/bot.py
lunarcord/builders.py
lunarcord/commands.py
lunarcord/configs.py
lunarcord/errors.py
lunarcord/future.py
lunarcord/tasks.py
lunarcord/ui.py
lunarcord/__core__/__init__.py
lunarcord/__core__/addons.py
lunarcord/__core__/gateway.py
lunarcord/__core__/permissions.py
lunarcord/__core__/requests.py
lunarcord/__core__/types.py
lunarcord-1.1.0.dist-info/METADATA
lunarcord-1.1.0.dist-info/WHEEL
lunarcord-1.1.0.dist-info/licenses/LICENSE
lunarcord-1.1.0.dist-info/RECORD
