Metadata-Version: 2.3
Name: lunarcord
Version: 1.1.0
Summary: A Library for easily writing multi-purpose Discord Bots.
Author-email: Revolno <revolnohtyp@gmail.com>
License-File: LICENSE
Classifier: License :: OSI Approved :: MIT License
Classifier: Operating System :: OS Independent
Classifier: Programming Language :: Python :: 3
Requires-Python: >=3.8
Requires-Dist: aiohttp>=3.9.1
Requires-Dist: discord-emoji>=1.4.2
Requires-Dist: orjson>=3.10.4
Requires-Dist: pillow>=10.1.0
